avicenna/__init__.py
avicenna/avicenna.py
avicenna/cli.py
avicenna/evaluation_setup.py
avicenna/execution_handler.py
avicenna/feature_collector.py
avicenna/feature_extractor.py
avicenna/features.py
avicenna/generator.py
avicenna/helpers.py
avicenna/input.py
avicenna/learner.py
avicenna/logger.py
avicenna/monads.py
avicenna/oracle.py
avicenna/pattern_learner.py
avicenna/performance_evaluator.py
avicenna/report.py
avicenna/result_table.py
avicenna_formalizations/__init__.py
avicenna_formalizations/calculator.py
avicenna_formalizations/fastapi_api.py
avicenna_formalizations/genson.py
avicenna_formalizations/heartbeat.py
avicenna_formalizations/middle.py
avicenna_formalizations/patterns.toml
avicenna_formalizations/patterns_islearn.toml
avicenna_formalizations/tests4py.py
avicenna-0.9.0.dist-info/LICENSE
avicenna-0.9.0.dist-info/METADATA
avicenna-0.9.0.dist-info/WHEEL
avicenna-0.9.0.dist-info/entry_points.txt
avicenna-0.9.0.dist-info/top_level.txt
avicenna-0.9.0.dist-info/RECORD
