Metadata-Version: 2.1
Name: avicenna
Version: 0.9.0
Summary: AVICENNA: Semantic Debugging
Home-page: https://github.com/martineberlein/semantic-debugging
Author: Martin Eberlein
Author-email: martin.eberlein@informatik.hu-berlin.de
License: MIT License
Project-URL: Bug Tracker, https://github.com/martineberlein/semantic-debugging/issues
Classifier: Intended Audience :: Science/Research
Classifier: License :: OSI Approved :: MIT License
Classifier: Programming Language :: Python :: 3.10
Classifier: Operating System :: OS Independent
Classifier: Topic :: Scientific/Engineering
Classifier: Topic :: Software Development :: Testing
License-File: LICENSE
Requires-Dist: fuzzingbook (~=1.1)
Requires-Dist: isla-solver (>=1.14.1)
Requires-Dist: islearn (>=0.2.15)
Requires-Dist: shap (>=0.41)
Requires-Dist: lightgbm (>=3.3.2)
Requires-Dist: pandas (>=1.4.4)
Requires-Dist: numpy (>=1.23.2)
Requires-Dist: scikit-learn (>=1.1.2)
Provides-Extra: dev
Requires-Dist: pytest (>=7.2.0) ; extra == 'dev'
Requires-Dist: twine ; extra == 'dev'
Requires-Dist: flaky (>=3.7.0) ; extra == 'dev'
